pnmac_common/__init__.py
pnmac_common/configreader.py
pnmac_common/formatter.py
pnmac_common/scrubber.py
pnmac_common-0.1.9.dist-info/METADATA
pnmac_common-0.1.9.dist-info/RECORD
pnmac_common-0.1.9.dist-info/WHEEL
pnmac_common-0.1.9.dist-info/top_level.txt
