Metadata-Version: 2.1
Name: pnmac-common
Version: 0.1.9
Summary: A set of utilities to use
Home-page: https://gitlab.pnmac.com/martech/pnmac-common-utilities
Author: Example Author
Author-email: none@example.com
License: UNKNOWN
Platform: UNKNOWN
Classifier: Programming Language :: Python :: 3
Classifier: License :: OSI Approved :: MIT License
Classifier: Operating System :: OS Independent
